poetry_conda/__init__.py
poetry_conda/plugin.py
poetry_conda-0.1.4.dist-info/LICENSE
poetry_conda-0.1.4.dist-info/METADATA
poetry_conda-0.1.4.dist-info/WHEEL
poetry_conda-0.1.4.dist-info/entry_points.txt
poetry_conda-0.1.4.dist-info/RECORD
