Metadata-Version: 2.3
Name: poetry-conda
Version: 0.1.4
Summary: Poetry plugin that allows for the creation of virtual environments using Poetry, without interfering with the Conda environment in which Poetry is installed
License: MIT
Author: Renan Santos
Author-email: renan.engmec@gmail.com
Requires-Python: >=3.9,<4
Classifier: Development Status :: 5 - Production/Stable
Classifier: Intended Audience :: Developers
Classifier: License :: OSI Approved :: MIT License
Classifier: Operating System :: OS Independent
Classifier: Programming Language :: Python
Classifier: Programming Language :: Python :: 3
Classifier: Programming Language :: Python :: 3.9
Classifier: Programming Language :: Python :: 3.10
Classifier: Programming Language :: Python :: 3.11
Classifier: Programming Language :: Python :: 3.12
Classifier: Programming Language :: Python :: 3.13
Classifier: Programming Language :: Python :: 3 :: Only
Classifier: Typing :: Typed
Requires-Dist: poetry (>=1.5.0,<3)
Project-URL: Documentation, https://github.com/renan-r-santos/poetry-conda
Project-URL: Repository, https://github.com/renan-r-santos/poetry-conda
